flagpole/__init__.py
flagpole-1.1.1.dist-info/LICENSE
flagpole-1.1.1.dist-info/METADATA
flagpole-1.1.1.dist-info/WHEEL
flagpole-1.1.1.dist-info/top_level.txt
flagpole-1.1.1.dist-info/RECORD
