Metadata-Version: 2.1
Name: flagpole
Version: 1.1.1
Summary: Flagpole is a Flag arg parser to build out a dictionary with optional keys.
Home-page: https://github.com/scriptsrc/flagpole
Author: Patrick Kelley
Author-email: patrickbarrettkelley@gmail.com
License: UNKNOWN
Platform: UNKNOWN
Provides-Extra: dev
Requires-Dist: pre-commit ; extra == 'dev'
Provides-Extra: docs
Provides-Extra: tests
Requires-Dist: pytest ; extra == 'tests'
Requires-Dist: mock ; extra == 'tests'
